{
  "project_info": {
    "project_number": "706339694572",
    "project_id": "bunnii-media-2",
    "storage_bucket": "bunnii-media-2.firebasestorage.app"
  },
  "client": [
    {
      "client_info": {
        "mobilesdk_app_id": "1:706339694572:android:9a0627093b3a5e49a942c9",
        "android_client_info": {
          "package_name": "com.aistudio.studycontroller.pvkqrx"
        }
      },
      "oauth_client": [
        {
          "client_id": "706339694572-9qga8r9734icftao4kocdavbjlt4b1ee.apps.googleusercontent.com",
          "client_type": 3
        }
      ],
      "api_key": [
        {
          "current_key": "AIzaSyBrZZnE3yAoavkxntHGGp2rXPWsljBBdoE"
        }
      ],
      "services": {
        "appinvite_service": {
          "other_platform_oauth_client": [
            {
              "client_id": "706339694572-9qga8r9734icftao4kocdavbjlt4b1ee.apps.googleusercontent.com",
              "client_type": 3
            }
          ]
        }
      }
    }
  ],
  "configuration_version": "1"
}
